simple_tools/__init__.py
simple_tools/_typing.py
simple_tools/ai/__init__.py
simple_tools/ai/classifier.py
simple_tools/ai/config.py
simple_tools/ai/deepseek_client.py
simple_tools/ai/prompts.py
simple_tools/ai/summarizer.py
simple_tools/ai/text_analyzer.py
simple_tools/ai/version_analyzer.py
simple_tools/cli.py
simple_tools/config.py
simple_tools/core/batch_rename.py
simple_tools/core/duplicate_finder.py
simple_tools/core/duplicate_finder.py.bak
simple_tools/core/file_organizer.py
simple_tools/core/file_tool.py
simple_tools/core/summarize_cmd.py
simple_tools/core/text_replace.py
simple_tools/utils/__init__.py
simple_tools/utils/config_loader.py
simple_tools/utils/errors.py
simple_tools/utils/formatter.py
simple_tools/utils/performance_optimizer.py
simple_tools/utils/progress.py
simple_tools/utils/smart_interactive.py
sumu_simple_tools-0.3.0.dist-info/LICENSE
sumu_simple_tools-0.3.0.dist-info/METADATA
sumu_simple_tools-0.3.0.dist-info/WHEEL
sumu_simple_tools-0.3.0.dist-info/entry_points.txt
sumu_simple_tools-0.3.0.dist-info/RECORD
