Metadata-Version: 2.3
Name: sumu-simple-tools
Version: 0.3.0
Summary: 一个简单实用的Python工具集，专注解决日常工作中的实际问题
License: MIT
Keywords: tools,cli,file,rename,duplicate,organize
Author: peacock
Author-email: weipeacock@gmail.com
Requires-Python: >=3.13.3,<4.0.0
Classifier: Intended Audience :: Developers
Classifier: License :: OSI Approved :: MIT License
Classifier: Operating System :: OS Independent
Classifier: Programming Language :: Python :: 3
Classifier: Programming Language :: Python :: 3.13
Classifier: Topic :: Software Development :: Libraries :: Python Modules
Classifier: Topic :: Utilities
Requires-Dist: click (>=8.2.1,<9.0.0)
Requires-Dist: httpx[http2] (>=0.28.1,<0.29.0)
Requires-Dist: logfire (>=3.16.0,<4.0.0)
Requires-Dist: pydantic (>=2.11.5,<3.0.0)
Requires-Dist: pydantic-settings (>=2.9.1,<3.0.0)
Requires-Dist: pypdf (>=5.6.0,<6.0.0)
Requires-Dist: python-docx (>=1.1.2,<2.0.0)
Requires-Dist: pyyaml (>=6.0,<7.0)
Project-URL: Homepage, https://github.com/sumu2025/simple-tools
Project-URL: Repository, https://github.com/sumu2025/simple-tools
